{
  "manifest": {
    "apis": {
      "custom": {
        "endpoint": {
          "uri": "arn:aws:lambda:us-east-1:645852837239:function:8e0c9af8-6567-4b2d-be06-b998e0434bec:Release_0"
        },
        "regions": {
          "EU": {
            "endpoint": {
              "uri": "arn:aws:lambda:eu-west-1:645852837239:function:8e0c9af8-6567-4b2d-be06-b998e0434bec:Release_0"
            }
          },
          "NA": {
            "endpoint": {
              "uri": "arn:aws:lambda:us-east-1:645852837239:function:8e0c9af8-6567-4b2d-be06-b998e0434bec:Release_0"
            }
          },
          "FE": {
            "endpoint": {
              "uri": "arn:aws:lambda:us-west-2:645852837239:function:8e0c9af8-6567-4b2d-be06-b998e0434bec:Release_0"
            }
          }
        }
      }
    },
    "publishingInformation": {
      "locales": {
        "de-DE": {
          "name": "alexa-typescript-starter"
        },
        "it-IT": {
          "name": "alexa-typescript-starter"
        }
      }
    }
  }
}
